Metadata-Version: 2.1
Name: thecolorapi
Version: 1.0.0
Summary: A simple python wrapper for 𝗧𝗵𝗲 𝗖𝗼𝗹𝗼𝗿 𝗔𝗣𝗜 ❤🧡💛💚💙💜
Home-page: https://github.com/RealA10N/thecolorapi
Author: RealA10N
Author-email: downtown2u@gmail.com
License: MIT
Project-URL: Source code, https://github.com/RealA10N/thecolorapi
Project-URL: Website, https://www.thecolorapi.com/
Keywords: color python api wrapper-api colorscheme colors
Platform: UNKNOWN
Classifier: Development Status :: 5 - Production/Stable
Classifier: License :: OSI Approved :: MIT License
Classifier: Operating System :: OS Independent
Classifier: Programming Language :: Python :: 3.6
Classifier: Programming Language :: Python :: 3.7
Classifier: Programming Language :: Python :: 3.8
Classifier: Programming Language :: Python :: 3.9
Requires-Python: >=3.6
